picox/__init__.py
picox/cli.py
picox/compiler.py
picox/detect.py
picox/exceptions.py
picox/logconfig.py
picox/upy.py
picox/commands/compiled.py
raw_commands/DOWNLOAD_FILE.py
raw_commands/UPLOAD_FILE.py
picox-1.4.0.dist-info/LICENCE
picox-1.4.0.dist-info/METADATA
picox-1.4.0.dist-info/WHEEL
picox-1.4.0.dist-info/entry_points.txt
picox-1.4.0.dist-info/top_level.txt
picox-1.4.0.dist-info/RECORD
