Metadata-Version: 2.1
Name: picox
Version: 1.4.0
Summary: Tools for working with a Rasbperry Pi Pico running MicroPython
Author: Harvey
License: MIT License
Project-URL: Homepage, https://github.com/SparkyTheAlbino/picox
Project-URL: Documentation, https://github.com/SparkyTheAlbino/picox
Project-URL: Repository, https://github.com/SparkyTheAlbino/picox.git
Project-URL: Issues, https://github.com/SparkyTheAlbino/picox/issues
Keywords: pico,serial,RaspberryPi
Classifier: License :: OSI Approved :: MIT License
Classifier: Programming Language :: Python
Classifier: Programming Language :: Python :: 3
Classifier: Environment :: Console
Classifier: Operating System :: OS Independent
Classifier: Topic :: Software Development :: Embedded Systems
License-File: LICENCE
Requires-Dist: pyserial ==3.5
Requires-Dist: pyreadline3 ==3.4.1 ; platform_system == "Windows"
Provides-Extra: dev
Requires-Dist: build ; extra == 'dev'
Requires-Dist: twine ; extra == 'dev'
